<model>
    <mount>//OPNsense/Tinc</mount>
    <version>1.0.2</version>
    <description>
        OPNsense Tinc VPN
    </description>
    <items>
        <networks>
            <network type="ArrayField">
                <id type="AutoNumberField">
                    <ValidationMessage>ID should be a number.</ValidationMessage>
                    <Required>Y</Required>
                </id>
                <name type="TextField">
                    <Required>Y</Required>
                    <mask>/^([0-9a-zA-Z]){1,50}$/u</mask>
                    <ValidationMessage>The name should contain only alphanumeric characters.</ValidationMessage>
                </name>
                <hostname type="TextField">
                    <Required>Y</Required>
                    <mask>/^([0-9a-zA-Z\_]){1,1024}$/u</mask>
                    <ValidationMessage>Please specify a valid hostname.</ValidationMessage>
                </hostname>
                <extaddress type="TextField">
                    <Required>Y</Required>
                    <mask>/^([0-9a-zA-Z\.,_\-:]){0,1024}$/u</mask>
                </extaddress>
                <extport type="IntegerField">
                    <Required>Y</Required>
                    <default>655</default>
                    <MinimumValue>1</MinimumValue>
                    <MaximumValue>65535</MaximumValue>
                    <ValidationMessage>Port number must be between 1...65535</ValidationMessage>
                </extport>
                <intaddress type="NetworkField">
                    <Required>Y</Required>
                    <WildcardEnabled>N</WildcardEnabled>
                </intaddress>
                <subnet type="NetworkField">
                    <Required>Y</Required>
                    <WildcardEnabled>N</WildcardEnabled>
                    <NetMaskRequired>Y</NetMaskRequired>
                    <FieldSeparator>,</FieldSeparator>
                </subnet>
                <pingtimeout type="IntegerField">
                    <Required>Y</Required>
                    <default>5</default>
                    <MinimumValue>1</MinimumValue>
                    <MaximumValue>65535</MaximumValue>
                    <ValidationMessage>Ping timeout must be between 1...65535</ValidationMessage>
                </pingtimeout>
                <privkey type="TextField">
                    <Required>Y</Required>
                </privkey>
                <pubkey type="TextField">
                    <Required>Y</Required>
                </pubkey>
                <cipher type="JsonKeyValueStoreField">
                    <Required>Y</Required>
                    <Multiple>N</Multiple>
                    <ConfigdPopulateAct>tinc list ciphers</ConfigdPopulateAct>
                    <SourceFile>/tmp/tinc_current_cipher_options.index</SourceFile>
                    <default>aes-256-cbc</default>
                </cipher>
                <mode type="OptionField">
                  <Required>Y</Required>
                  <default>router</default>
                  <OptionValues>
                      <router>router</router>
                      <switch>switch</switch>
                  </OptionValues>
                </mode>
                <PMTUDiscovery type="BooleanField">
                    <default>1</default>
                    <Required>Y</Required>
                </PMTUDiscovery>
                <enabled type="BooleanField">
                    <default>1</default>
                    <Required>Y</Required>
                </enabled>
                <debuglevel type="OptionField">
                    <Required>Y</Required>
                    <default>ip</default>
                    <OptionValues>
                        <d0>[0] start/stop, serious errors</d0>
                        <d1>[1] +all connections</d1>
                        <d2>[2] +script status</d2>
                        <d3>[3] +all requests</d3>
                        <d4>[4] +meta socket</d4>
                        <d5>[5] +network traffic</d5>
                    </OptionValues>
                    <ValidationMessage>debug level needs to be between 0 (default) and 5 (highest)</ValidationMessage>
                </debuglevel>
            </network>
        </networks>
        <hosts>
            <host type="ArrayField">
                <network type="ModelRelationField">
                    <Model>
                        <hosts>
                            <source>OPNsense.Tinc.Tinc</source>
                            <items>networks.network</items>
                            <display>name</display>
                        </hosts>
                    </Model>
                    <ValidationMessage>Related network not found</ValidationMessage>
                    <Required>Y</Required>
                </network>
                <hostname type="TextField">
                    <Required>Y</Required>
                    <mask>/^([0-9a-zA-Z\_]){1,1024}$/u</mask>
                    <ValidationMessage>Please specify a valid hostname.</ValidationMessage>
                </hostname>
                <extport type="IntegerField">
                    <Required>Y</Required>
                    <default>655</default>
                    <MinimumValue>1</MinimumValue>
                    <MaximumValue>65535</MaximumValue>
                    <ValidationMessage>Port number must be between 1...65535</ValidationMessage>
                </extport>
                <extaddress type="TextField">
                    <Required>Y</Required>
                    <mask>/^([0-9a-zA-Z\.,_\-:]){0,1024}$/u</mask>
                </extaddress>
                <subnet type="NetworkField">
                    <Required>Y</Required>
                    <WildcardEnabled>N</WildcardEnabled>
                    <NetMaskRequired>Y</NetMaskRequired>
                    <FieldSeparator>,</FieldSeparator>
                </subnet>
                <pubkey type="TextField">
                    <Required>Y</Required>
                </pubkey>
                <cipher type="JsonKeyValueStoreField">
                    <Required>Y</Required>
                    <Multiple>N</Multiple>
                    <ConfigdPopulateAct>tinc list ciphers</ConfigdPopulateAct>
                    <SourceFile>/tmp/tinc_current_cipher_options.index</SourceFile>
                    <default>aes-256-cbc</default>
                </cipher>
                <connectTo type="BooleanField">
                    <default>1</default>
                    <Required>Y</Required>
                </connectTo>
                <enabled type="BooleanField">
                    <default>1</default>
                    <Required>Y</Required>
                </enabled>
            </host>
        </hosts>
    </items>
</model>
