<model>
    <mount>//wol</mount>
    <description>Wake On Lan configuration</description>
    <version>1.0.0</version>
    <items>
      <wolentry type="ArrayField">
        <interface type="InterfaceField">
            <Required>Y</Required>
            <multiple>N</multiple>
            <default></default>
            <filters>
                <enable>/^(?!0).*$/</enable>
                <if>/^(?!openvpn|ipsec|enc).*$/i</if>
            </filters>
        </interface>
        <mac type="TextField">
            <Required>Y</Required>
            <multiple>N</multiple>
            <mask>/^((?:[a-f0-9]{2}:){5}(?:[a-f0-9]{2}))$/</mask>
            <default>00:00:00:00:00:00</default>
        </mac>
        <descr type="TextField">
            <Required>N</Required>
            <multiple>N</multiple>
            <default></default>
        </descr>
      </wolentry>
    </items>
</model>
